{
  "cik": 713676,
  "company_name": "PNC_Financial_Services",
  "ticker": "PNC",
  "form_type": "8-K",
  "filing_date": "2023-01-24",
  "period": "",
  "accession_number": "0000713676-23-000012",
  "file_url": "https://www.sec.gov/Archives/edgar/data/713676/0000713676-23-000012-index.html",
  "text": "                                              \n                UNITED STATES                 \n                                              \n                                              \n      SECURITIES AND EXCHANGE COMMISSION      \n                                              \n                                              \n            Washington, D.C. 20549            \n                                              \n                                              \n                   FORM 8-K                   \n                                              \n                                              \n                CURRENT REPORT                \n                                              \n    Pursuant to Section 13 OR 15(d) of The    \n       Securities Exchange Act of 1934        \n                                              \n               January 19, 2023               \n                                              \n                                              \n   Date of Report (Date of earliest event     \n   reported)                                  \n                                              \n                                              \n    THEPNC FINANCIAL SERVICES GROUP, INC.     \n                                              \n(Exact name of registrant as specified in its \n                   charter)                   \n                                              \n       Commission File Number 001-09718       \n                                              \n                                              \n  Pennsylvania           25-1435979           \n  (State or other        (I.R.S. Employer     \n  jurisdiction of                             \n  incorporation)         Identification No.)  \n                                              \n                                              \n            The Tower at PNC Plaza            \n                                              \n                                              \n               300 Fifth Avenue               \n                                              \n                                              \n     Pittsburgh, Pennsylvania 15222-2401      \n                                              \n   (Address of principal executive offices,   \n             including zip code)              \n                                              \n               ( 888) 762-2265                \n                                              \n(Registrant\u2019s telephone number, including area\n                    code)                     \n                                              \n                Not Applicable                \n                                              \n  (Former name or former address, if changed  \n              since last report)              \nCheck the appropriate box below if the Form\n8-K filing is intended to simultaneously\nsatisfy the filing obligation of the\nregistrant under any of the following\nprovisions:\n                                              \n       Written communications pursuant to     \n  \u2610    Rule 425 under the Securities Act (17  \n       CFR 230.425)                           \n       Soliciting material pursuant to Rule   \n  \u2610    14a-12 under the Exchange Act (17 CFR  \n       240.14a-12)                            \n       Pre-commencement communications        \n  \u2610    pursuant to Rule 14d-2(b) under the    \n       Exchange Act (17 CFR 240.14d-2(b))     \n       Pre-commencement communications        \n  \u2610    pursuant to Rule 13e-4(c) under the    \n       Exchange Act (17 CFR 240.13e-4(c))     \n                                              \nSecurities registered pursuant to 12(b) of the\nAct:\n                                              \n                                Name of Each  \n  Title of       Trading        Exchange      \n  Each Class     Symbol(s)      on Which      \n                                Registered    \n  Common                        New York      \n  Stock, par     PNC            Stock         \n  value $5.00                   Exchange      \n                                              \nIndicate by check mark whether the registrant\nis an emerging growth company as defined in\nRule 405 of the Securities Act of 1933\n(\u00a7230.405 of this chapter) or Rule 12b-2 of\nthe Securities Exchange Act of 1934\n(\u00a7240.12b-2 of this chapter). Emerging growth\ncompany \u2610\n\nIf an emerging growth company, indicate by\ncheck mark if the registrant has elected not\nto use the extended transition period for\ncomplying with any new or revised financial\naccounting standards provided pursuant to\nSection 13(a) of the Exchange\n                                              \n  Item 8.01 Other Events.                     \n                                              \nOn January 24, 2023, The PNC Financial\nServices Group, Inc. (the \u201cCorporation\u201d)\ncompleted the public offer and sale of (a)\n$1,250,000,000 aggregate principal amount of\nits 4.758% Fixed Rate/Floating Rate Senior\nNotes due January 26, 2027, and (b)\n$1,500,000,000 aggregate principal amount of\nits 5.068% Fixed Rate/Floating Rate Senior\nNotes due January 24, 2034 (collectively, the\n\u201cNotes\u201d). The Notes were sold pursuant to an\nUnderwriting Agreement dated January 19, 2023\n(the \u201cUnderwriting Agreement\u201d) entered into by\nthe Corporation, PNC Capital Markets LLC,\nBarclays Capital Inc., Citigroup Global\nMarkets Inc., and Goldman Sachs & Co. LLC. The\nUnderwriting Agreement is attached to this\nCurrent Report on Form 8-K as Exhibit 1.1 and\nis incorporated into this Item 8.01 by\nreference.\n\nThe Notes were issued under an Indenture,\ndated as of September 6, 2012 (the \u201cBase\nIndenture\u201d), as amended and supplemented by a\nFirst Supplemental Indenture, dated as of\nApril 23, 2021 (the \u201cSupplemental Indenture\u201d\nand together with the Base Indenture, the\n\u201cIndenture\u201d), between the Corporation and The\nBank of New York Mellon, as trustee.\n\nThe underwritten offering described in this\nCurrent Report on Form 8-K is more fully\ndescribed in the prospectus supplements, each\ndated January 19, 2023, and filed with the\nSecurities and Exchange Commission (the\n\u201cCommission\u201d) on January 20, 2023, to the\naccompanying prospectus filed with the\nCommission on December 13, 2021, as part of\nthe Company\u2019s Registration Statement on Form\nS-3ASR (File No. 333-261622) (the\n\u201cRegistration Statement\u201d). The above\ndescription of the Underwriting Agreement and\nthe Indenture is qualified in its entirety by\nreference to the full text of such agreements.\nCopies of the Underwriting Agreement, the Base\nIndenture, the Supplemental Indenture and the\nForm of each Note are filed or incorporated by\nreference as Exhibits 1.1, 4.1, 4.2, 4.3 and\n4.4, respectively.\n\nCopies of the legality opinions delivered by\nLaura Gleason, counsel to the Corporation in\nconnection with the issuance of the Notes, are\nattached hereto as Exhibits 5.1 and 5.2.\n\nThis Current Report on Form 8-K is being filed\nfor the purpose of filing the attached\ndocuments in connection with the issuance of\nthe Notes as exhibits to the Registration\nStatement and such exhibits are hereby\nincorporated by reference into the\nRegistration Statement.\n                                              \n  Item 9.01 Financial Statements and          \n  Exhibits.                                   \n                                              \n(d) Exhibits.\n                                              \n                              Method of       \n                              Filing          \n            Description       Filed herewith  \n            Underwriting      Incorporated    \n            Agreement         herein by       \n            dated as of       reference to    \n            January 19,       Exhibit 4.19    \n            2023              of Form S-3     \n            Indenture,        filed on        \n            dated as of       January 15,     \n            September 6,      2010, as        \n            2012, between     amended by      \n            the               Post-Effective  \n            Corporation       Amendment No.   \n  Number    and The Bank      1 filed on      \n  1.1       of New York       September 6,    \n  4.1       Mellon            2012            \n \u2500\u2500\u2500\u2500\u2500\u2500\u2500\u2500\u2500\u2500\u2500\u2500\u2500\u2500\u2500\u2500\u2500\u2500\u2500\u2500\u2500\u2500\u2500\u2500\u2500\u2500\u2500\u2500\u2500\u2500\u2500\u2500\u2500\u2500\u2500\u2500\u2500\u2500\u2500\u2500\u2500\u2500\u2500\u2500 \n            Supplemental                      \n            Indenture,        Incorporated    \n            dated as of       herein by       \n            April 23,         reference to    \n  4.2       2021, between     Exhibit 4.2 of  \n            the               Form 8-K filed  \n            Corporation       on April 23,    \n            and The Bank      2021            \n            of New York                       \n            Mellon                            \n            Form of 4.758%                    \n            Fixed                             \n            Rate/Floating                     \n  4.3       Rate Senior       Filed herewith  \n            Note due                          \n            January 26,                       \n            2027                              \n            Form of 5.068%                    \n            Fixed                             \n            Rate/Floating                     \n  4.4       Rate Senior       Filed herewith  \n            Note due                          \n            January 24,                       \n            2034                              \n            Opinion of                        \n            Laura Gleason                     \n            in connection                     \n            with the                          \n  5.1       4.758% Fixed      Filed herewith  \n            Rate/Floating                     \n            Rate Senior                       \n            Notes due                         \n            January 26,                       \n            2027                              \n            Opinion of                        \n            Laura Gleason                     \n            in connection                     \n            with the                          \n  5.2       5.068% Fixed      Filed herewith  \n            Rate/Floating                     \n            Rate Senior                       \n            Notes due                         \n            January 24,                       \n            2034                              \n            Consent of                        \n            Laura Gleason                     \n            in connection                     \n            with the                          \n            4.758% Fixed                      \n  23.1      Rate/Floating     Filed herewith  \n            Rate Senior                       \n            Notes due                         \n            January 26,                       \n            2027 (included                    \n            in Exhibit                        \n            5.1)                              \n            Consent of                        \n            Laura Gleason                     \n            in connection                     \n            with the                          \n            5.068% Fixed                      \n  23.2      Rate/Floating     Filed herewith  \n            Rate Senior                       \n            Notes due                         \n            January 24,                       \n            2034 (included                    \n            in Exhibit                        \n            5.2)                              \n            The cover page                    \n            of this                           \n            Current Report                    \n  104       on Form 8-K,                      \n            formatted as                      \n            an inline                         \n            XBRL.                             \n                                              \n                                              \n                  SIGNATURE                   \n                                              \nPursuant to the requirements of the Securities\nExchange Act of 1934, the registrant has duly\ncaused this report to be signed on its behalf\nby the undersigned hereunto duly authorized.\n                                              \n                       THE PNC                \n                       FINANCI\u2026               \n                       SERVICES               \n                       GROUP,                 \n                       INC.        /s/        \n           January     (Regist\u2026    Gregory    \n  Date:    24, 2023    By:         H. Kozich  \n \u2500\u2500\u2500\u2500\u2500\u2500\u2500\u2500\u2500\u2500\u2500\u2500\u2500\u2500\u2500\u2500\u2500\u2500\u2500\u2500\u2500\u2500\u2500\u2500\u2500\u2500\u2500\u2500\u2500\u2500\u2500\u2500\u2500\u2500\u2500\u2500\u2500\u2500\u2500\u2500\u2500\u2500\u2500\u2500 \n                                   Gregory    \n                                   H. Kozich  \n                                   Senior     \n                                   Vice       \n                                   President  \n                                   and        \n                                   Controll\u2026  \n                                              \n                    - 3 -                     \n"
}