{
  "cik": 927971,
  "company_name": "Bank_of_Montreal",
  "ticker": "BMO",
  "form_type": "6-K",
  "filing_date": "2021-12-03",
  "period": "",
  "accession_number": "0001193125-21-347998",
  "file_url": "https://www.sec.gov/Archives/edgar/data/927971/0001193125-21-347998-index.html",
  "text": "FORM 6-K SECURITIES AND EXCHANGE COMMISSION\nWashington, D.C. 20549 Report of Foreign\nPrivate Issuer Pursuant to Rule 13a-16or\n15d-16 of the Securities Exchange Act of 1934\n                                              \n  For the month of:     Commission File       \n  December, 2021        Number: 001-13354     \n                                              \nBANK OF MONTREAL (Name of Registrant)\n                                              \n  100 King Street                             \n  West                                        \n  1 First Canadian      129 rue               \n  Place                 Saint-Jacques         \n  Toronto, Ontario      Montreal, Quebec      \n  Canada, M5X 1A1       Canada, H2Y 1L6       \n  (Executive            -Head Office          \n  Offices)                                    \n                                              \nIndicate by check mark whether the registrant\nfiles or will file annual reports under cover\nof Form 20-For Form 40-F: Form 20-F \u2610Form 40-F\n\u2611 Indicate by check mark if the registrant is\nsubmitting the Form 6-Kin paper as permitted\nby Regulation S-TRule 101(b)(1): \u2610 Indicate by\ncheck mark if the registrant is submitting the\nForm 6-Kin paper as permitted by Regulation\nS-TRule 101(b)(7): \u2610\n\nSIGNATURES Pursuant to the requirements of the\nSecurities Exchange Act of 1934, the\nregistrant has duly caused this report to be\nsigned on its behalf by the undersigned,\nthereunto duly authorized.\n                                              \n                       BANK OF                \n                       MONTREAL               \n                                   /s/        \n               By:                 Tayfun     \n                                   Tuzun      \n               Name:               Tayfun     \n                                   Tuzun      \n                                   Chief      \n               Title:              Financial  \n                                   Officer    \n  Date:                            /s/        \n  December\u00a0    By:                 Barbara    \n  3, 2021                          M. Muir    \n               Name:               Barbara    \n                                   M. Muir    \n               Title:              Corporate  \n                                   Secretary  \n                                              \nEXHIBIT INDEX\n                                              \n  Exhibit    Description of Exhibit           \n  99.1       Canadian Independent Auditors\u0092    \n             Report dated December 3rd, 2021  \n                                              \n"
}