{
  "cik": 1045520,
  "company_name": "Canadian_Imperial_Bank_of_Commerce",
  "ticker": "CM",
  "form_type": "6-K",
  "filing_date": "2022-08-04",
  "period": "",
  "accession_number": "0001193125-22-212688",
  "file_url": "https://www.sec.gov/Archives/edgar/data/1045520/0001193125-22-212688-index.html",
  "text": "                                              \n   UNITED STATES                              \n                                              \n                                              \n   SECURITIES AND EXCHANGE COMMISSION         \n                                              \nWashington, D.C. 20549\n\nFORM 6-K\n\nReport of Foreign Private Issuer\n\nPursuant to Rule 13a-16or 15d-16\n\nunder the Securities Exchange Act of 1934\n\nFor the month of August 2022\n\nCommission File Number: 1-14678\n                                              \n   CANADIAN IMPERIAL BANK OF COMMERCE         \n                                              \n(Translation of registrant\u0092s name into\nEnglish)\n\n81 Bay Street\n\nCIBC Square\n\nToronto, Ontario\n\nCanada M5J OE7\n\n(Address of principal executive offices)\n\nIndicate by check mark whether the registrant\nfiles or will file annual reports under cover\nof Form 20-F or Form 40-F:\n\nForm\n20-F \u2610 Form 40-F \u2612\n\nIndicate by check mark if the registrant is\nsubmitting the Form 6-K in paper as permitted\nby Regulation S-T Rule 101(b)(1): \u2610\n\nIndicate by check mark if the registrant is\nsubmitting the Form 6-K in paper as permitted\nby Regulation S-T Rule 101(b)(7): \u2610\n\nTHIS REPORT ON FORM 6-K AND THE EXHIBITS\nHERETO SHALL BE DEEMED TO BE INCORPORATED BY\nREFERENCE AS EXHIBITS TO\nCANADIAN IMPERIAL BANK OF COMMERCE\u0092S\nREGISTRATION STATEMENT ON FORM F-3 (FILE NO.\n333-259240) AND TO BE A PART THEREOF FROM THE\nDATE ON WHICH THIS REPORT IS\nFURNISHED, TO THE EXTENT NOT SUPERSEDED BY\nDOCUMENTS OR REPORTS SUBSEQUENTLY FILED OR\nFURNISHED.\n\nSIGNATURES Pursuant to the requirements of the\nSecurities Exchange Act of 1934, the\nregistrant has duly caused this report to be\nsigned on its behalf by the undersigned,\nthereunto duly authorized.\n                                              \n                       CANADIAN               \n  Date:                IMPERIAL               \n  August\u00a04,            BANK OF                \n  2022                 COMMERCE               \n \u2500\u2500\u2500\u2500\u2500\u2500\u2500\u2500\u2500\u2500\u2500\u2500\u2500\u2500\u2500\u2500\u2500\u2500\u2500\u2500\u2500\u2500\u2500\u2500\u2500\u2500\u2500\u2500\u2500\u2500\u2500\u2500\u2500\u2500\u2500\u2500\u2500\u2500\u2500\u2500\u2500\u2500\u2500\u2500 \n               By:                /s/ Wojtek  \n                                  Niebrzydo\u2026  \n               Name:              Wojtek      \n                                  Niebrzydo\u2026  \n                                  Vice-Pres\u2026  \n                                  Global      \n               Title:             Term        \n                                  Funding,    \n                                  Treasury    \n                                              \nEXHIBIT INDEX\n                                              \n       Opinion of Mayer Brown LLP, U.S.       \n  5.1  counsel for Canadian Imperial Bank of  \n       Commerce, as to                        \n       the validity of the securities         \n                                              \n                                              \n       Opinion of Blake, Cassels              \n  5.2  & Graydon LLP, Canadian counsel for    \n       Canadian Imperial Bank of Commerce,    \n       as to the validity of the securities   \n                                              \n                                              \n  23.1  Consent of Mayer Brown LLP (included  \n        in Exhibit 5.1 above)                 \n                                              \n                                              \n  23.2  Consent of Blake, Cassels\u00a0& Graydon   \n        LLP (included in Exhibit 5.2 above)   \n                                              \n                                              \n        Underwriting Agreement, dated as of   \n        July                                  \n        28, 2022, by and among Canadian       \n        Imperial Bank of Commerce and CIBC    \n        World Markets Corp., Barclays         \n        Capital Inc., BofA Securities, Inc.,  \n        Citigroup Global Markets Inc. and     \n        Wells Fargo Securities, LLC, as       \n        representatives of the several        \n  99.1  underwriters                          \n \u2500\u2500\u2500\u2500\u2500\u2500\u2500\u2500\u2500\u2500\u2500\u2500\u2500\u2500\u2500\u2500\u2500\u2500\u2500\u2500\u2500\u2500\u2500\u2500\u2500\u2500\u2500\u2500\u2500\u2500\u2500\u2500\u2500\u2500\u2500\u2500\u2500\u2500\u2500\u2500\u2500\u2500\u2500\u2500 \n                                              \n"
}