{
  "cik": 895421,
  "company_name": "Morgan_Stanley",
  "ticker": "MS",
  "form_type": "4",
  "filing_date": "2023-10-10",
  "period": "",
  "accession_number": "0000899243-23-019945",
  "file_url": "https://www.sec.gov/Archives/edgar/data/895421/0000899243-23-019945-index.html",
  "text": "OMB APPROVAL \n OMB Number: 3235-0287 \n Estimated average burden \n hours per response: 0.5\n\nFORM 4\n\nCheck this box if no longer subject to Section\n16. Form 4 or Form 5 obligations may continue.\nSee Instruction 1(b).\n\nUNITED STATES SECURITIES AND EXCHANGE\nCOMMISSION\n Washington, D.C. 20549\n\nSTATEMENT OF CHANGES IN BENEFICIAL OWNERSHIP\n\nFiled pursuant to Section 16(a) of the\nSecurities Exchange Act of 1934\n or Section 30(h) of the Investment Company\nAct of 1940\n                                              \n                       2. Issuer Name and     \n  1. Name and Address  Ticker or Trading      \n  of Reporting         Symbol                 \n  Person*              WESTERN ASSET          \n  MORGAN STANLEY1585   MUNICIPAL PARTNERS     \n  BROADWAYNEW YORK NY  FUND INC. [MNP]        \n  10036                3. Date of Earliest    \n  1a. IRS/SSN          Transaction            \n  Identification       (Month/Day/Year)       \n  Number of Reporting  10/05/2023             \n  Person               4. If Amendment, Date  \n                       of Original Filed      \n                       (Month/Day/Year)       \n                       DirectorOfficer (give  \n                       title below)10%        \n                       OwnerOther (specify    \n                       below)                 \n                       Form filed by One      \n                       Reporting PersonForm   \n                       filed by More than     \n                       One Reporting Person   \n                                              \n                                              \n  ** Signature of Reporting                   \n  Person                          Date        \n  /s/ By: Morgan Stanley, By:     10/10/2023  \n  Joseph Maehr, Authorized                    \n  Signatory                                   \n                                              \nNote: File three copies of this Form, one of\nwhich must be manually signed. If space is\ninsufficient, see Instruction 6 for procedure.\n Persons who respond to the collection of\ninformation contained in this form are not\nrequired to respond unless the form displays a\ncurrently valid OMB Number.\n"
}